pymmdbserver/__init__.py
pymmdbserver/api.py
pymmdbserver/py.typed
pymmdbserver-1.2.1.dist-info/METADATA
pymmdbserver-1.2.1.dist-info/WHEEL
pymmdbserver-1.2.1.dist-info/entry_points.txt
pymmdbserver-1.2.1.dist-info/licenses/LICENSE
pymmdbserver-1.2.1.dist-info/RECORD
