Metadata-Version: 2.4
Name: pymmdbserver
Version: 1.2.1
Summary: Python CLI and module for MMDB Server
License-Expression: BSD-3-Clause
License-File: LICENSE
Author: Raphaël Vinot
Author-email: raphael.vinot@circl.lu>
Requires-Python: >=3.10
Classifier: Development Status :: 5 - Production/Stable
Classifier: Environment :: Console
Classifier: Intended Audience :: Information Technology
Classifier: Intended Audience :: Science/Research
Classifier: Intended Audience :: Telecommunications Industry
Classifier: Operating System :: POSIX :: Linux
Classifier: Programming Language :: Python :: 3
Classifier: Programming Language :: Python :: 3.10
Classifier: Programming Language :: Python :: 3.11
Classifier: Programming Language :: Python :: 3.12
Classifier: Programming Language :: Python :: 3.13
Classifier: Programming Language :: Python :: 3.14
Classifier: Topic :: Internet
Classifier: Topic :: Security
Provides-Extra: docs
Requires-Dist: Sphinx (>=9.1.0) ; (python_version >= "3.12") and (extra == "docs")
Requires-Dist: requests (>=2.32.5)
Project-URL: Documentation, https://pymmdbserver.readthedocs.io/en/latest/
Project-URL: Repository, https://github.com/Lookyloo/PyMmdbServer
Project-URL: issues, https://github.com/Lookyloo/PyMmdbServer
